{
    "configurations": [
        {
            "browse": {
                "databaseFilename": "",
                "limitSymbolsToIncludedHeaders": true
            },
            "includePath": [
                "/home/sst/catkin_lins/devel/include/**",
                "/opt/ros/melodic/include/**",
                "/home/sst/catkin_lins/src/LINS---LiDAR-inertial-SLAM/lins/include/**",
                "/usr/include/**"
            ],
            "name": "ROS",
            "intelliSenseMode": "gcc-x64",
            "compilerPath": "/usr/bin/gcc",
            "cStandard": "gnu11",
            "cppStandard": "gnu++14"
        }
    ],
    "version": 4
}